aiko/__init__.py
aiko/application.py
aiko/context.py
aiko/cookies.py
aiko/request.py
aiko/response.py
aiko/server.py
aiko/utils.py
aiko/worker.py
aiko-0.2.3.dist-info/METADATA
aiko-0.2.3.dist-info/RECORD
aiko-0.2.3.dist-info/WHEEL
aiko-0.2.3.dist-info/top_level.txt
aiokoa/__init__.py
aiokoa/application.py
aiokoa/context.py
aiokoa/request.py
aiokoa/response.py
aiokoa/server.py
aiokoa/utils.py
aiokoa/worker.py
