Metadata-Version: 2.1
Name: aiko
Version: 0.2.3
Summary: UNKNOWN
Home-page: https://github.com/zeromake/aiko
Author: zeromake
Author-email: a390720046@gmail.com
Maintainer: zeromake
Maintainer-email: a390720046@gmail.com
License: MIT
Project-URL: Code, https://github.com/zeromake/aiko
Project-URL: Issue tracker, https://github.com/zeromake/aiko/issues
Platform: any
Classifier: Environment :: Web Environment
Classifier: License :: OSI Approved :: MIT License
Classifier: Programming Language :: Python :: 3 :: Only
Classifier: Programming Language :: Python :: 3.5
Classifier: Programming Language :: Python :: 3.6
Classifier: Programming Language :: Python :: Implementation :: CPython
Classifier: Programming Language :: Python :: Implementation :: PyPy
Classifier: Topic :: Software Development :: Libraries :: Application Frameworks
Classifier: Topic :: Software Development :: Libraries :: Python Modules
Requires-Python: >=3.5
Requires-Dist: httptools (>=0.0.11)
